cwx_aiml_app_template/__init__.py
cwx_aiml_app_template/cli.py
cwx_aiml_app_template/generator.py
cwx_aiml_app_template/templates/__init__.py
cwx_aiml_app_template/templates/dockerfile_template
cwx_aiml_app_template/templates/gitignore_template
cwx_aiml_app_template/templates/readme_template.md
cwx_aiml_app_template/templates/structure.py
cwx_aiml_app_template-0.1.6.dist-info/LICENSE
cwx_aiml_app_template-0.1.6.dist-info/METADATA
cwx_aiml_app_template-0.1.6.dist-info/WHEEL
cwx_aiml_app_template-0.1.6.dist-info/entry_points.txt
cwx_aiml_app_template-0.1.6.dist-info/top_level.txt
cwx_aiml_app_template-0.1.6.dist-info/RECORD
