Metadata-Version: 2.1
Name: cwx-aiml-app-template
Version: 0.1.6
Home-page: https://github.com/rajeshmore1/cwx-aiml-app-template
Classifier: Programming Language :: Python :: 3
Classifier: License :: OSI Approved :: MIT License
Classifier: Operating System :: OS Independent
Requires-Python: >=3.8
License-File: LICENSE
Requires-Dist: Click
Requires-Dist: rich
